{
  "id": 9416,
  "name": "Phosani's Nightmare",
  "drops": [
    {
      "name": "Big bones",
      "quantity": "1",
      "rarity": "Always",
      "itemId": 532
    },
    {
      "name": "Nightmare staff",
      "quantity": "1",
      "rarity": "1/533",
      "itemId": 24422
    },
    {
      "name": "Inquisitor's great helm",
      "quantity": "1",
      "rarity": "1/700",
      "itemId": 24419
    },
    {
      "name": "Inquisitor's hauberk",
      "quantity": "1",
      "rarity": "1/700",
      "itemId": 24420
    },
    {
      "name": "Inquisitor's plateskirt",
      "quantity": "1",
      "rarity": "1/700",
      "itemId": 24421
    },
    {
      "name": "Inquisitor's mace",
      "quantity": "1",
      "rarity": "1/1250",
      "itemId": 24417
    },
    {
      "name": "Eldritch orb",
      "quantity": "1",
      "rarity": "1/1600",
      "itemId": 24517
    },
    {
      "name": "Harmonised orb",
      "quantity": "1",
      "rarity": "1/1600",
      "itemId": 24511
    },
    {
      "name": "Volatile orb",
      "quantity": "1",
      "rarity": "1/1600",
      "itemId": 24514
    },
    {
      "name": "Cosmic rune",
      "quantity": "247–420",
      "rarity": "4/100",
      "itemId": 564
    },
    {
      "name": "Nature rune",
      "quantity": "165–305",
      "rarity": "4/100",
      "itemId": 561
    },
    {
      "name": "Death rune",
      "quantity": "165–305",
      "rarity": "4/100",
      "itemId": 560
    },
    {
      "name": "Blood rune",
      "quantity": "343–765",
      "rarity": "4/100",
      "itemId": 565
    },
    {
      "name": "Soul rune",
      "quantity": "110–228",
      "rarity": "4/100",
      "itemId": 566
    },
    {
      "name": "Cannonball",
      "quantity": "137–382",
      "rarity": "4/100",
      "itemId": 2
    },
    {
      "name": "Rune arrow",
      "quantity": "412–957",
      "rarity": "3/100",
      "itemId": 892
    },
    {
      "name": "Mithril ore",
      "quantity": "165–305",
      "rarity": "5/100",
      "itemId": 447
    },
    {
      "name": "Coal",
      "quantity": "220–458",
      "rarity": "4/100",
      "itemId": 453
    },
    {
      "name": "Gold ore",
      "quantity": "165–305",
      "rarity": "4/100",
      "itemId": 444
    },
    {
      "name": "Adamantite ore",
      "quantity": "40–95",
      "rarity": "4/100",
      "itemId": 449
    },
    {
      "name": "Magic logs",
      "quantity": "40–95",
      "rarity": "4/100",
      "itemId": 1513
    },
    {
      "name": "Grimy cadantine",
      "quantity": "13–26",
      "rarity": "4/100",
      "itemId": 215
    },
    {
      "name": "Grimy torstol",
      "quantity": "13–26",
      "rarity": "4/100",
      "itemId": 219
    },
    {
      "name": "Snapdragon seed",
      "quantity": "5–10",
      "rarity": "3/100",
      "itemId": 5300
    },
    {
      "name": "Uncut emerald",
      "quantity": "33–75",
      "rarity": "3/100",
      "itemId": 1621
    },
    {
      "name": "Uncut ruby",
      "quantity": "27–60",
      "rarity": "3/100",
      "itemId": 1619
    },
    {
      "name": "Runite ore",
      "quantity": "11–26",
      "rarity": "2/100",
      "itemId": 451
    },
    {
      "name": "Bass",
      "quantity": "16–29",
      "rarity": "6/100",
      "itemId": 365
    },
    {
      "name": "Shark",
      "quantity": "13–26",
      "rarity": "6/100",
      "itemId": 385
    },
    {
      "name": "Prayer potion(3)",
      "quantity": "8–15",
      "rarity": "5/100",
      "itemId": 139
    },
    {
      "name": "Sanfew serum(3)",
      "quantity": "6–12",
      "rarity": "5/100",
      "itemId": 10927
    },
    {
      "name": "Saradomin brew(3)",
      "quantity": "8–15",
      "rarity": "5/100",
      "itemId": 6687
    },
    {
      "name": "Zamorak brew(3)",
      "quantity": "8–15",
      "rarity": "5/100",
      "itemId": 189
    },
    {
      "name": "Coins",
      "quantity": "41417–73590",
      "rarity": "2/100",
      "itemId": 995
    },
    {
      "name": "Clue scroll (elite)",
      "quantity": "1",
      "rarity": "1/35",
      "itemId": 21524
    },
    {
      "name": "Slepey tablet",
      "quantity": "1",
      "rarity": "1/100",
      "itemId": 25837
    },
    {
      "name": "Parasitic egg",
      "quantity": "1",
      "rarity": "1/200",
      "itemId": 25838
    },
    {
      "name": "Little nightmare",
      "quantity": "1",
      "rarity": "1/1400",
      "itemId": 24491
    },
    {
      "name": "Jar of dreams",
      "quantity": "1",
      "rarity": "1/4000",
      "itemId": 24495
    }
  ]
}